README.md
setup.py
versipy/__init__.py
versipy/__main__.py
versipy/common.py
versipy/versipy.py
versipy.egg-info/PKG-INFO
versipy.egg-info/SOURCES.txt
versipy.egg-info/dependency_links.txt
versipy.egg-info/entry_points.txt
versipy.egg-info/requires.txt
versipy.egg-info/top_level.txt