Metadata-Version: 2.1
Name: versipy
Version: 0.1.dev3
Summary: Versatile version and medatada managment across the python packaging ecosystem, integrated with git
Home-page: https://github.com/a-slide/versipy
Author: Adrien Leger
Author-email: contact@adrienleger.com
License: GPLv3
Platform: UNKNOWN
Classifier: Development Status :: 3 - Alpha
Classifier: Intended Audience :: Science/Research
Classifier: Topic :: Scientific/Engineering :: Bio-Informatics
Classifier: License :: OSI Approved :: GNU General Public License v3 (GPLv3)
Classifier: Programming Language :: Python :: 3
Requires-Python: >=3.6
